macrobot_paper.py
macrobot_paper-0.1.6.dist-info/entry_points.txt
macrobot_paper-0.1.6.dist-info/WHEEL
macrobot_paper-0.1.6.dist-info/METADATA
macrobot_paper-0.1.6.dist-info/RECORD
