Metadata-Version: 2.1
Name: macrobot-paper
Version: 0.1.6
Summary: 
Author: Stefanie Lueck
Author-email: lueck@ipk-gatersleben.de
Requires-Python: >=3.7,<4.0
Classifier: Programming Language :: Python :: 3
Classifier: Programming Language :: Python :: 3.7
Classifier: Programming Language :: Python :: 3.8
Requires-Dist: numpy (>=1.18.3,<2.0.0)
Requires-Dist: opencv-python (>=4.2.0,<5.0.0)
Requires-Dist: scikit-image (>=0.16.2,<0.17.0)
